{
    "GAugO": {
        "cora": {
            "gcn": {
                "f1_score": 0.8355999,
                "std": 0.00456508,
                "alpha": 1.0,
                "beta": 0.8,
                "temp": 1.2,
                "pretrain_ep": 160,
                "pretrain_nc": 30,
                "warmup": 0
            },
            "gat": {
                "f1_score": 0.8221999,
                "std": 0.0077304592360350815,
                "alpha": 0.02,
                "beta": 2.3,
                "temp": 1.7,
                "pretrain_ep": 175,
                "pretrain_nc": 45,
                "warmup": 1
            },
            "gsage": {
                "f1_score": 0.82,
                "std": 0.004827007354458862,
                "alpha": 0.13,
                "beta": 3.2,
                "temp": 1.0,
                "pretrain_ep": 195,
                "pretrain_nc": 35,
                "warmup": 2
            },
            "jknet": {
                "f1_score": 0.8045,
                "std": 0.009162423260251606,
                "alpha": 0.02,
                "beta": 3.8,
                "temp": 0.1,
                "pretrain_ep": 75,
                "pretrain_nc": 10,
                "warmup": 10
            }
        },
        "citeseer": {
            "gcn": {
                "f1_score": 0.73305,
                "std": 0.007172691266184548,
                "alpha": 0.79,
                "beta": 2.9,
                "temp": 0.5,
                "pretrain_ep": 70,
                "pretrain_nc": 215,
                "warmup": 0
            },
            "gat": {
                "f1_score": 0.716249,
                "std": 0.010624852940158743,
                "alpha": 0.18,
                "beta": 0.4,
                "temp": 1.6,
                "pretrain_ep": 210,
                "pretrain_nc": 10,
                "warmup": 8
            },
            "gsage": {
                "f1_score": 0.7265999999999999,
                "std": 0.00692387174924551,
                "alpha": 0.08,
                "beta": 0.0,
                "temp": 1.4,
                "pretrain_ep": 290,
                "pretrain_nc": 10,
                "warmup": 5
            },
            "jknet": {
                "f1_score": 0.6971499999999999,
                "std": 0.013947311568900991,
                "alpha": 0.17,
                "beta": 0.0,
                "temp": 0.8,
                "pretrain_ep": 145,
                "pretrain_nc": 5,
                "warmup": 0
            }
        },
        "ppi": {
            "gcn": {
                "f1_score": 0.46759581971933517,
                "std": 0.004080315157827575,
                "alpha": 0.28,
                "beta": 0.5,
                "temp": 0.9,
                "pretrain_ep": 245,
                "pretrain_nc": 140,
                "warmup": 2
            },
            "gat": {
                "f1_score": 0.446814757614913,
                "std": 0.008489154492390514,
                "alpha": 0.01,
                "beta": 3.1,
                "temp": 0.9,
                "pretrain_ep": 65,
                "pretrain_nc": 155,
                "warmup": 8
            },
            "gsage": {
                "f1_score": 0.45223802559499565,
                "std": 0.00551736949793766,
                "alpha": 0.43,
                "beta": 1.8,
                "temp": 1.9,
                "pretrain_ep": 85,
                "pretrain_nc": 215,
                "warmup": 0
            },
            "jknet": {
                "f1_score": 0.5362943025563041,
                "std": 0.0022671646455270232,
                "alpha": 0.19,
                "beta": 0.4,
                "temp": 2.0,
                "pretrain_ep": 165,
                "pretrain_nc": 260,
                "warmup": 0
            }
        },
        "blogcatalog": {
            "gcn": {
                "f1_score": 0.7591396371632766,
                "std": 0.0024212140447889417,
                "alpha": 0.43,
                "beta": 2.8,
                "temp": 1.0,
                "pretrain_ep": 5,
                "pretrain_nc": 235,
                "warmup": 9
            },
            "gat": {
                "f1_score": 0.7100054975261132,
                "std": 0.0113331070808734,
                "alpha": 0.04,
                "beta": 2.0,
                "temp": 0.3,
                "pretrain_ep": 70,
                "pretrain_nc": 300,
                "warmup": 7
            },
            "gsage": {
                "f1_score": 0.7387300714678395,
                "std": 0.0035034599977319483,
                "alpha": 0.25,
                "beta": 1.4,
                "temp": 0.6,
                "pretrain_ep": 5,
                "pretrain_nc": 105,
                "warmup": 9
            },
            "jknet": {
                "f1_score": 0.7100604727872457,
                "std": 0.006293166804289919,
                "alpha": 0.0,
                "beta": 2.2,
                "temp": 1.3,
                "pretrain_ep": 165,
                "pretrain_nc": 290,
                "warmup": 5
            }
        },
        "flickr": {
            "gcn": {
                "f1_score": 0.6221761267207242,
                "std": 0.0032740010430640223,
                "alpha": 0.05,
                "beta": 2.5,
                "temp": 0.3,
                "pretrain_ep": 5,
                "pretrain_nc": 300,
                "warmup": 10
            },
            "gat": {
                "f1_score": 0.5190699603997737,
                "std": 0.004677015003454424,
                "alpha": 0.25,
                "beta": 2.3,
                "temp": 0.6,
                "pretrain_ep": 80,
                "pretrain_nc": 250,
                "warmup": 1
            },
            "gsage": {
                "f1_score": 0.5631812181783896,
                "std": 0.005501172623002805,
                "alpha": 0.42,
                "beta": 3.0,
                "temp": 0.5,
                "pretrain_ep": 150,
                "pretrain_nc": 280,
                "warmup": 10
            },
            "jknet": {
                "f1_score": 0.5574863284933057,
                "std": 0.0050929503123485695,
                "alpha": 0.5,
                "beta": 0.1,
                "temp": 0.7,
                "pretrain_ep": 40,
                "pretrain_nc": 265,
                "warmup": 10
            }
        },
        "airport": {
            "gcn": {
                "f1_score": 0.6142857142857142,
                "std": 0.008756924957904859,
                "alpha": 0.62,
                "beta": 0.9,
                "temp": 2.1,
                "pretrain_ep": 290,
                "pretrain_nc": 295,
                "warmup": 9
            },
            "gat": {
                "f1_score": 0.5462785114045619,
                "std": 0.008535025815841165,
                "alpha": 0.37,
                "beta": 1.5,
                "temp": 0.9,
                "pretrain_ep": 5,
                "pretrain_nc": 275,
                "warmup": 4
            },
            "gsage": {
                "f1_score": 0.5705474189675869,
                "std": 0.006645067228378417,
                "alpha": 0.48,
                "beta": 0.2,
                "temp": 1.3,
                "pretrain_ep": 35,
                "pretrain_nc": 115,
                "warmup": 8
            },
            "jknet": {
                "f1_score": 0.6038415366146458,
                "std": 0.010165168369755841,
                "alpha": 0.81,
                "beta": 1.6,
                "temp": 0.4,
                "pretrain_ep": 40,
                "pretrain_nc": 75,
                "warmup": 10
            }
        }
    },
    "GAugM": {
        "cora": {
            "gcn": {
                "f1_score": 0.8516,
                "std": 0.0038,
                "i": 5,
                "rm_pct": 2,
                "add_pct": 57
            },
            "gsage": {
                "f1_score": 0.8316,
                "std": 0.0038,
                "i": 2,
                "rm_pct": 1,
                "add_pct": 80
            },
            "gat": {
                "f1_score": 0.8205,
                "std": 0.0104,
                "i": 2,
                "rm_pct": 1,
                "add_pct": 68
            },
            "jknet": {
                "f1_score": 0.8184,
                "std": 0.0094,
                "i": 2,
                "rm_pct": 1,
                "add_pct": 72
            }
        },
        "citeseer": {
            "gcn": {
                "f1_score": 0.7225,
                "std": 0.0041,
                "i": 2,
                "rm_pct": 0,
                "add_pct": 46
            },
            "gsage": {
                "f1_score": 0.7116,
                "std": 0.0034,
                "i": 2,
                "rm_pct": 2,
                "add_pct": 37
            },
            "jknet": {
                "f1_score": 0.6824,
                "std": 0.0123,
                "i": 2,
                "rm_pct": 2,
                "add_pct": 48
            }
        },
        "blogcatalog": {
            "gcn": {
                "f1_score": 0.7756,
                "std": 0.0039,
                "i": 1,
                "rm_pct": 1,
                "add_pct": 4
            },
            "gat": {
                "f1_score": 0.7082,
                "std": 0.0103,
                "i": 2,
                "rm_pct": 58,
                "add_pct": 4
            },
            "gsage": {
                "f1_score": 0.7704,
                "std": 0.0036,
                "i": 3,
                "rm_pct": 2,
                "add_pct": 7
            },
            "jknet": {
                "f1_score": 0.7189,
                "std": 0.0049,
                "i": 2,
                "rm_pct": 14,
                "add_pct": 7
            }
        },
        "ppi": {
            "gcn": {
                "f1_score": 0.4349,
                "std": 0.0025,
                "i": 2,
                "rm_pct": 0,
                "add_pct": 0
            },
            "gat": {
                "f1_score": 0.4278,
                "std": 0.0087,
                "i": 2,
                "rm_pct": 17,
                "add_pct": 80
            },
            "gsage": {
                "f1_score": 0.4112,
                "std": 0.0103,
                "i": 3,
                "rm_pct": 2,
                "add_pct": 80
            },
            "jknet": {
                "f1_score": 0.4738,
                "std": 0.006,
                "i": 1,
                "rm_pct": 45,
                "add_pct": 21
            }
        },
        "flickr": {
            "gcn": {
                "f1_score": 0.6818,
                "std": 0.0066,
                "i": 2,
                "rm_pct": 29,
                "add_pct": 0
            },
            "gat": {
                "f1_score": 0.637,
                "std": 0.0091,
                "i": 2,
                "rm_pct": 80,
                "add_pct": 2
            },
            "gsage": {
                "f1_score": 0.6521,
                "std": 0.0041,
                "i": 3,
                "rm_pct": 80,
                "add_pct": 0
            },
            "jknet": {
                "f1_score": 0.6569,
                "std": 0.0076,
                "i": 2,
                "rm_pct": 80,
                "add_pct": 0
            }
        },
        "airport": {
            "gcn": {
                "f1_score": 0.6116,
                "std": 0.0045,
                "i": 1,
                "rm_pct": 21,
                "add_pct": 0
            },
            "gat": {
                "f1_score": 0.59,
                "std": 0.0063,
                "i": 3,
                "rm_pct": 21,
                "add_pct": 38
            },
            "gsage": {
                "f1_score": 0.6011,
                "std": 0.0046,
                "i": 1,
                "rm_pct": 21,
                "add_pct": 3
            },
            "jknet": {
                "f1_score": 0.602,
                "std": 0.0059,
                "i": 1,
                "rm_pct": 21,
                "add_pct": 12
            }
        }
    },
    "AdaEdge": {
        "cora": {
            "gcn": {
                "f1_score": 0.8189500000000001,
                "std": 0.006807899822999718,
                "add_first": 1,
                "n_add": 1050,
                "n_remove": 4221,
                "conf_add": 0.9476970623856602,
                "conf_remove": 0.5800951794747702
            },
            "gat": {
                "f1_score": 0.8202999999999999,
                "std": 0.006116371473349185,
                "add_first": 1,
                "n_add": 2793,
                "n_remove": 4756,
                "conf_add": 0.8770933553619108,
                "conf_remove": 0.7431313025473302
            },
            "gsage": {
                "f1_score": 0.8152999999999999,
                "std": 0.004148493702538292,
                "add_first": 1,
                "n_add": 2670,
                "n_remove": 4097,
                "conf_add": 0.9982507322529197,
                "conf_remove": 0.5031853427209241
            },
            "jknet": {
                "f1_score": 0.8043999999999999,
                "std": 0.01212600511297925,
                "add_first": 0,
                "n_add": 5066,
                "n_remove": 2817,
                "conf_add": 0.5439511279644962,
                "conf_remove": 0.5723453462399495
            }
        },
        "citeseer": {
            "gcn": {
                "f1_score": 0.7280500000000001,
                "std": 0.007137751746873788,
                "add_first": 1,
                "n_add": 3283,
                "n_remove": 3560,
                "conf_add": 0.5484196403281784,
                "conf_remove": 0.8226824409963941
            },
            "gat": {
                "f1_score": 0.711,
                "std": 0.0062209324059983116,
                "add_first": 0,
                "n_add": 2023,
                "n_remove": 1490,
                "conf_add": 0.8077973529075654,
                "conf_remove": 0.7075919741312733
            },
            "gsage": {
                "f1_score": 0.71305,
                "std": 0.007883368569336335,
                "add_first": 0,
                "n_add": 3019,
                "n_remove": 807,
                "conf_add": 0.5260593264360576,
                "conf_remove": 0.9740054151151799
            },
            "jknet": {
                "f1_score": 0.68885,
                "std": 0.012055185606202803,
                "add_first": 1,
                "n_add": 3360,
                "n_remove": 1808,
                "conf_add": 0.8131664636500419,
                "conf_remove": 0.666065591458308
            }
        },
        "airports": {
            "gcn": {
                "f1_score": 0.5716686674669869,
                "std": 0.008382756422615172,
                "add_first": 0,
                "n_add": 11256,
                "n_remove": 4691,
                "conf_add": 0.5088593614515954,
                "conf_remove": 0.8575637024618079
            },
            "gat": {
                "f1_score": 0.5449987995198078,
                "std": 0.018737780748135154,
                "add_first": 1,
                "n_add": 11596,
                "n_remove": 12215,
                "conf_add": 0.5003352250045214,
                "conf_remove": 0.7763281732419552
            },
            "gsage": {
                "f1_score": 0.5714285714285715,
                "std": 0.005205158076513517,
                "add_first": 0,
                "n_add": 12031,
                "n_remove": 10470,
                "conf_add": 0.6344996029191976,
                "conf_remove": 0.6651406112101845
            },
            "jknet": {
                "f1_score": 0.5940576230492197,
                "std": 0.009688068534034458,
                "add_first": 0,
                "n_add": 5649,
                "n_remove": 2951,
                "conf_add": 0.9799597197917709,
                "conf_remove": 0.5635835617761165
            }
        },
        "flickr": {
            "gcn": {
                "f1_score": 0.6117480671318121,
                "std": 0.005213577951061126,
                "add_first": 0,
                "n_add": 80100,
                "n_remove": 169002,
                "conf_add": 0.890923537563037,
                "conf_remove": 0.62124056527628
            },
            "gat": {
                "f1_score": 0.4815104657740902,
                "std": 0.010459312212787448,
                "add_first": 0,
                "n_add": 34270,
                "n_remove": 151857,
                "conf_add": 0.9120800810424818,
                "conf_remove": 0.7408916171468733
            },
            "gsage": {
                "f1_score": 0.5770318687535358,
                "std": 0.0049670155615738785,
                "add_first": 0,
                "n_add": 117961,
                "n_remove": 110221,
                "conf_add": 0.7123367527025519,
                "conf_remove": 0.8472521240188635
            },
            "jknet": {
                "f1_score": 0.5699321138977936,
                "std": 0.0029366951629553905,
                "add_first": 1,
                "n_add": 133277,
                "n_remove": 192117,
                "conf_add": 0.5968952684946967,
                "conf_remove": 0.8316530822310493
            }
        },
        "ppi": {
            "gcn": {
                "f1_score": 0.4363850269151358,
                "std": 0.0018944732824987811,
                "add_first": 1,
                "n_add": 23061,
                "n_remove": 48201,
                "conf_add": 0.7092432589337163,
                "conf_remove": 0.7209534440809202
            },
            "gat": {
                "f1_score": 0.42562535298195386,
                "std": 0.008542373100286322,
                "add_first": 0,
                "n_add": 20074,
                "n_remove": 17642,
                "conf_add": 0.8032092353908711,
                "conf_remove": 0.8949998076993941
            },
            "gsage": {
                "f1_score": 0.41579194087893906,
                "std": 0.007762927890667338,
                "add_first": 1,
                "n_add": 84286,
                "n_remove": 74951,
                "conf_add": 0.6066896459380346,
                "conf_remove": 0.8480019096138598
            },
            "jknet": {
                "f1_score": 0.4480719479124822,
                "std": 0.009221534275401788,
                "add_first": 0,
                "n_add": 87287,
                "n_remove": 145980,
                "conf_add": 0.5272794553869935,
                "conf_remove": 0.8076044099879962
            }
        },
        "blogcatalog": {
            "gcn": {
                "f1_score": 0.7534496976360637,
                "std": 0.0028835493982802426,
                "add_first": 0,
                "n_add": 35271,
                "n_remove": 171361,
                "conf_add": 0.9785026609262446,
                "conf_remove": 0.9126355803842885
            },
            "gat": {
                "f1_score": 0.6818993952721275,
                "std": 0.021294643626954584,
                "add_first": 0,
                "n_add": 519,
                "n_remove": 59640,
                "conf_add": 0.6494496243147848,
                "conf_remove": 0.5064189479102948
            },
            "gsage": {
                "f1_score": 0.735747663551402,
                "std": 0.0035182824929731746,
                "add_first": 0,
                "n_add": 8323,
                "n_remove": 98174,
                "conf_add": 0.865582076977589,
                "conf_remove": 0.864413403001219
            },
            "jknet": {
                "f1_score": 0.7073117097306212,
                "std": 0.004414824961608316,
                "add_first": 0,
                "n_add": 8927,
                "n_remove": 23262,
                "conf_add": 0.556667275665075,
                "conf_remove": 0.5504891220392711
            }
        }
    },
    "DropEdge": {
        "cora": {
            "gcn": {
                "f1_score": 0.82005,
                "std": 0.007877023549539465,
                "dropedge": 0.06699533884091742
            },
            "gsage": {
                "f1_score": 0.8156000000000001,
                "std": 0.004831148931672427,
                "dropedge": 0.11347081349435667
            },
            "gat": {
                "f1_score": 0.8185500000000001,
                "std": 0.0072420646227439505,
                "dropedge": 0.11536642663803405
            },
            "jknet": {
                "f1_score": 0.8041500000000001,
                "std": 0.01081330199337833,
                "dropedge": 0.7523066665840696
            }
        },
        "citeseer": {
            "gcn": {
                "f1_score": 0.7177499999999999,
                "std": 0.002447456530637913,
                "dropedge": 0.1275293439912054
            },
            "gsage": {
                "f1_score": 0.70755,
                "std": 0.004614189292725159,
                "dropedge": 0.6438656430895608
            },
            "gat": {
                "f1_score": 0.7092,
                "std": 0.0047180504448342,
                "dropedge": 0.3390552860251006
            },
            "jknet": {
                "f1_score": 0.6935,
                "std": 0.010637198879404284,
                "dropedge": 0.7623021110891007
            }
        },
        "ppi": {
            "gcn": {
                "f1_score": 0.4353189801457639,
                "std": 0.002418687146436113,
                "dropedge": 0.010609972159486438
            },
            "gsage": {
                "f1_score": 0.4112013185594595,
                "std": 0.009709722404632103,
                "dropedge": 0.9890330311032427
            },
            "gat": {
                "f1_score": 0.45903022392290865,
                "std": 0.003146467920076924,
                "dropedge": 0.9573924408177268
            },
            "jknet": {
                "f1_score": 0.4627382625548872,
                "std": 0.0018454420979202566,
                "dropedge": 0.9265316212744581
            }
        },
        "blogcatalog:": {
            "gcn": {
                "f1_score": 0.7542468389224849,
                "std": 0.0033749113110270027,
                "dropedge": 0.2700010422226254
            },
            "gsage": {
                "f1_score": 0.7381390874106653,
                "std": 0.0042852501967905665,
                "dropedge": 0.40778361160643034
            },
            "gat": {
                "f1_score": 0.7085623969213855,
                "std": 0.0096919994723251,
                "dropedge": 0.6257458789276933
            },
            "jknet": {
                "f1_score": 0.7093457943925233,
                "std": 0.0042666965657195246,
                "dropedge": 0.5791136877803604
            }
        },
        "flickr": {
            "gcn": {
                "f1_score": 0.6137563643220819,
                "std": 0.0066113087672749725,
                "dropedge": 0.3341180229603983
            },
            "gsage": {
                "f1_score": 0.5840279087309069,
                "std": 0.007363726183001249,
                "dropedge": 0.5971157423799105
            },
            "gat": {
                "f1_score": 0.5004525740147087,
                "std": 0.016100039633554927,
                "dropedge": 0.5912825117203554
            },
            "jknet": {
                "f1_score": 0.5852159155195172,
                "std": 0.0066023001967871284,
                "dropedge": 0.49285054940748124
            }
        },
        "airports": {
            "gcn": {
                "f1_score": 0.5687875150060024,
                "std": 0.0060929544011762305,
                "dropedge": 0.19356316838870039
            },
            "gsage": {
                "f1_score": 0.5707082833133252,
                "std": 0.005112974655233349,
                "dropedge": 0.010598330296425403
            },
            "gat": {
                "f1_score": 0.5279111644657863,
                "std": 0.017128942570829288,
                "dropedge": 0.016328436793535527
            },
            "jknet": {
                "f1_score": 0.5911764705882352,
                "std": 0.010926842984812588,
                "dropedge": 0.014580810466312169
            }
        }
    }
}